instainteracts/__init__.py
instainteracts/helpers/__init__.py
instainteracts/helpers/const.py
instainteracts/helpers/options.py
instainteracts/InstaInteracts.py
instainteracts-1.0.3.dist-info/LICENSE
instainteracts-1.0.3.dist-info/METADATA
instainteracts-1.0.3.dist-info/WHEEL
instainteracts-1.0.3.dist-info/RECORD
