Metadata-Version: 2.1
Name: instainteracts
Version: 1.0.3
Summary: Instainteracts is an automation tool for Instagram interactions
Author: Manuel
Author-email: hi@manugmg.anonaddy.me
Requires-Python: >=3.11,<4.0
Classifier: Programming Language :: Python :: 3
Classifier: Programming Language :: Python :: 3.11
Requires-Dist: pyperclip (>=1.8.2,<2.0.0)
Requires-Dist: selenium (>=4.8.0,<5.0.0)
Requires-Dist: webdriver-manager (>=3.8.5,<4.0.0)
